Metadata-Version: 2.1
Name: notion-cobertos-fork
Version: 0.0.29
Summary: Fork of https://github.com/jamalex/notion-py
Home-page: https://github.com/Cobertos/notion-py
Author: Jamie Alexandre & Cobertos
Author-email: me@cobertos.com
License: UNKNOWN
Platform: UNKNOWN
Classifier: Programming Language :: Python :: 3
Classifier: License :: OSI Approved :: MIT License
Classifier: Operating System :: OS Independent
Requires-Python: >=3.5
License-File: LICENSE
Requires-Dist: requests
Requires-Dist: commonmark
Requires-Dist: bs4
Requires-Dist: tzlocal
Requires-Dist: python-slugify
Requires-Dist: dictdiffer
Requires-Dist: cached-property
